{
  "1594246686721069057": {
    "text": "Viele Fans winken ab. Und auch die Gastgeber hatten sich die Sache anders vorgestellt. Doch nur mit Pauschalkritik wird sich in #Qatar und im internationalen Fußball nichts bewegen. Was folgt aus der umstrittenen #WM2022, fragen @c_h_w_b und @cheh_faz. https://t.co/G2y1aB35YH",
    "created_at": "2022-11-20T08:30:04.000Z",
    "public_metrics": {
      "retweet_count": 5,
      "reply_count": 7,
      "like_count": 11,
      "quote_count": 0
    }
  },
  "1594246670983737344": {
    "text": "Ronaldo. Müller. Kane. Who will take out the Golden Boot in 2022? 🤔\n\n#SBSWorldCup #WeAllSpeakFootball #FIFAWorldCup https://t.co/YjAeVpxpT5",
    "created_at": "2022-11-20T08:30:00.000Z",
    "public_metrics": {
      "retweet_count": 0,
      "reply_count": 1,
      "like_count": 9,
      "quote_count": 0
    }
  },
  "1594246670341918720": {
    "text": "Bei Fußball kann man wegschauen. Aber hinschauen wenn es um #Menschenrechte geht. #BoycottQatar2022 #FIFAWorldCup #WM2022 @fdp_berlin @fdp https://t.co/s4aJ3gWMnd",
    "created_at": "2022-11-20T08:30:00.000Z",
    "public_metrics": {
      "retweet_count": 12,
      "reply_count": 12,
      "like_count": 90,
      "quote_count": 2
    }
  },
  "1594246668915974145": {
    "text": "Kein Public Viewing, keine  Tippspiele im Freundes- und Kollegenkreis, kein Fan-Artikel-Boom: Selten war die Vorfreude   auf eine Fußball-Weltmeisterschaft geringer als vor der heute beginnenden WM in Katar. \"Der Sonntag\" - kostenfrei in App &amp; eZeitung. https://t.co/90i9b0UoTs https://t.co/VDQM5ZNKei",
    "created_at": "2022-11-20T08:30:00.000Z",
    "public_metrics": {
      "retweet_count": 2,
      "reply_count": 0,
      "like_count": 1,
      "quote_count": 0
    }
  },
  "1594246668894892032": {
    "text": "Es ist soweit: Heute beginnt die Fußball-WM in Katar. ⚽ Ab 17:00 Uhr treffen die Gastgeber im Eröffnungsspiel auf Ecuador. Wir zeigen die Partie live im ZDF und im Stream 👉 https://t.co/PoT17To2Cl\n\n@FIFAWorldCup #FIFAWorldCup #WM2022 #QATECU https://t.co/TCc7D0oQag",
    "created_at": "2022-11-20T08:30:00.000Z",
    "public_metrics": {
      "retweet_count": 3,
      "reply_count": 70,
      "like_count": 24,
      "quote_count": 3
    }
  },
  "1594246562829451264": {
    "text": "Stell dir vor es ist #WM und keiner geht hin!\n\nJa, da werde ich schlecht gelaunt spät wach und bin schon so richtig in WM-Stimmung!\n\n#WMderSchande \n#WM2022 \n#BoycottQatar2022 \n#BoycottQatar",
    "created_at": "2022-11-20T08:29:34.000Z",
    "public_metrics": {
      "retweet_count": 1,
      "reply_count": 0,
      "like_count": 2,
      "quote_count": 0
    }
  },
  "1594246351008808961": {
    "text": "RT @StreamerSupRT: RT @runschilade: Heute geht die #WM2022 los - lol.\n\n#TwitchDE\n#SupportSmallStreamers #smallstreamers #wm #sport #FussballWM #goodmorning #SundayFunday #SmallStreamersConnect #SmallStreamerCommunity",
    "created_at": "2022-11-20T08:28:44.000Z",
    "public_metrics": {
      "retweet_count": 3,
      "reply_count": 0,
      "like_count": 2,
      "quote_count": 0
    }
  },
  "1594246349343838209": {
    "text": "RT @streamerwallcom: RT @runschilade: Heute geht die #WM2022 los - lol.\n\n#TwitchDE\n#SupportSmallStreamers #smallstreamers #wm #sport #FussballWM #goodmorning #SundayFunday #SmallStreamersConnect #SmallStreamerCommunity",
    "created_at": "2022-11-20T08:28:44.000Z",
    "public_metrics": {
      "retweet_count": 1,
      "reply_count": 0,
      "like_count": 1,
      "quote_count": 0
    }
  },
  "1594246347372240899": {
    "text": "RT @StreamDESupport: RT @runschilade: Heute geht die #WM2022 los - lol.\n\n#TwitchDE\n#SupportSmallStreamers #smallstreamers #wm #sport #FussballWM #goodmorning #SundayFunday #SmallStreamersConnect #SmallStreamerCommunity",
    "created_at": "2022-11-20T08:28:43.000Z",
    "public_metrics": {
      "retweet_count": 1,
      "reply_count": 0,
      "like_count": 0,
      "quote_count": 0
    }
  },
  "1594246346168586242": {
    "text": "RT @runschilade: Heute geht die #WM2022 los - lol.\n\n#TwitchDE\n#SupportSmallStreamers #smallstreamers #wm #sport #FussballWM #goodmorning #SundayFunday #SmallStreamersConnect #SmallStreamerCommunity",
    "created_at": "2022-11-20T08:28:43.000Z",
    "public_metrics": {
      "retweet_count": 1,
      "reply_count": 0,
      "like_count": 0,
      "quote_count": 0
    }
  },
  "1594246248898371585": {
    "text": "Ich werde die Fussball Weltmeisterschaft in Katar boykottieren",
    "created_at": "2022-11-20T08:28:20.000Z",
    "public_metrics": {
      "retweet_count": 0,
      "reply_count": 0,
      "like_count": 3,
      "quote_count": 0
    }
  },
  "1594246193558818817": {
    "text": "Ab heute beginnt die WM in Katar\n\nEs werden sich ALLE Spiele angeschaut!\n\nWarum?\n\nDie Arbeiter sollen nicht umsonst für uns gestorben sein\n\nDAS HEIẞT!\n\nVolle Unterstützung und Solidarität für die Gastarbeiter die während der Bauarbeiten ihr Leben verloren haben!\n\nSCHAUT DIE WM!",
    "created_at": "2022-11-20T08:28:06.000Z",
    "public_metrics": {
      "retweet_count": 2,
      "reply_count": 1,
      "like_count": 41,
      "quote_count": 0
    }
  },
  "1594246180221104129": {
    "text": "Nächster Schock für Frankreich - #Benzema verpasst die #WM2022\n\nhttps://t.co/MgXU55zTmb",
    "created_at": "2022-11-20T08:28:03.000Z",
    "public_metrics": {
      "retweet_count": 0,
      "reply_count": 0,
      "like_count": 3,
      "quote_count": 0
    }
  },
  "1594246061698469888": {
    "text": "Liebe #FIFAWorldCup Teilnehmer das ihr geldgeile Speichellecker seit beweist ihr ja schon durch eure Teilnahme. Aber wenn ich nur einen Funken Ehre im Leib habt tretet ihr nicht gegen den #iran an! \n#IranRevolution2022 #IranProtests2022",
    "created_at": "2022-11-20T08:27:35.000Z",
    "public_metrics": {
      "retweet_count": 1,
      "reply_count": 0,
      "like_count": 1,
      "quote_count": 0
    }
  },
  "1594246050264465408": {
    "text": "Beginn der WM in Qatar: Das traurigste Turnier aller Zeiten\n#123INFO https://t.co/gagJiPzOhq",
    "created_at": "2022-11-20T08:27:32.000Z",
    "public_metrics": {
      "retweet_count": 0,
      "reply_count": 0,
      "like_count": 0,
      "quote_count": 0
    }
  },
  "1594246050059100162": {
    "text": "Weltmeisterschaft in Qatar: Auf diese ­Spieler sollten Sie schauen\n#123INFO https://t.co/HjkrsTGAKt",
    "created_at": "2022-11-20T08:27:32.000Z",
    "public_metrics": {
      "retweet_count": 0,
      "reply_count": 0,
      "like_count": 0,
      "quote_count": 0
    }
  },
  "1594246018564263936": {
    "text": "Fußball ⚽️ schaue ich nicht, ich mache lieber “Rambazamba” 💦 Freute euch schon auf heute, 20.11. um 13 Uhr es wird mega hot 💦🍿💦 auf meinem Profil ➡️💦 https://t.co/LgChPP3yTq @ald17_17 @mydirtyhobbyen #FIFAWorldCup #RETWEEETME https://t.co/48O7ycRj9a",
    "created_at": "2022-11-20T08:27:25.000Z",
    "public_metrics": {
      "retweet_count": 70,
      "reply_count": 4,
      "like_count": 185,
      "quote_count": 0
    }
  },
  "1594246015481266176": {
    "text": "Matchday! Katar wegballern!\n\n#FIFAWorldCup 🏳️‍🌈 #Qatar2022 🌈 #HaremosHistoria🇪🇨 https://t.co/WZeTSuiDS5",
    "created_at": "2022-11-20T08:27:24.000Z",
    "public_metrics": {
      "retweet_count": 0,
      "reply_count": 0,
      "like_count": 0,
      "quote_count": 0
    }
  },
  "1594245989178945536": {
    "text": "FIFA-Präsident Gianni Infantino hält völlig (w)irre Rede auf der Auftaktpressekonferenz zur Fußball-WM in Katar. \n\n#WM #FIFA #GianniInfantino #Infantino #Fußball #Qatar #Katar #Spiel #Ball #Menschenrechte #Queer #Araber #Afrika #Frauen #Gastarbeiter #LGBTQ https://t.co/p8Kw6TVs7W",
    "created_at": "2022-11-20T08:27:18.000Z",
    "public_metrics": {
      "retweet_count": 1,
      "reply_count": 0,
      "like_count": 1,
      "quote_count": 0
    }
  },
  "1594245850171117571": {
    "text": "Die krassen Gegensätze in Katar werden während der WM noch sichtbarer – auch darum muss das Turnier für den Herrscher ein Erfolg werden. (Abo)\nhttps://t.co/kkywPDXvL2",
    "created_at": "2022-11-20T08:26:44.000Z",
    "public_metrics": {
      "retweet_count": 0,
      "reply_count": 0,
      "like_count": 1,
      "quote_count": 0
    }
  },
  "1594245735612125184": {
    "text": "18 #Werder-Spieler sind vor Niclas #Füllkrug mit #Deutschland zu einer #Weltmeisterschaft gefahren – diese Bremer waren schon dabei👉https://t.co/Ol1QmMFiDO\n\n#WM #WM2022 https://t.co/R4xjytMAmF",
    "created_at": "2022-11-20T08:26:17.000Z",
    "public_metrics": {
      "retweet_count": 3,
      "reply_count": 0,
      "like_count": 14,
      "quote_count": 0
    }
  },
  "1594245691567529986": {
    "text": "Legend vs legend ❤️ Best vs best 😍🖤\n#Messi𓃵 #FIFAWorldCup #Dreamers2022 #BabarAzam𓃵 #Kohli https://t.co/gIKrNy4l3u",
    "created_at": "2022-11-20T08:26:07.000Z",
    "public_metrics": {
      "retweet_count": 0,
      "reply_count": 0,
      "like_count": 2,
      "quote_count": 0
    }
  },
  "1594245635238232064": {
    "text": "Ob ihr die WM in #Qatar nun schaut oder nicht, wird sich nicht wirklich auswirken. Das muss jeder mit seinem eigenen Gewissen vereinbaren.\nUm das Turnier wirklich zu boykottieren, ist es wichtig keinerlei Merch zu kaufen, denn darüber kommt das Geld rein.",
    "created_at": "2022-11-20T08:25:53.000Z",
    "public_metrics": {
      "retweet_count": 0,
      "reply_count": 0,
      "like_count": 2,
      "quote_count": 0
    }
  },
  "1594245484692254722": {
    "text": "Endlich hat de FIFA Präsident das gesagt was vielen  unter den Nägeln brennt .Diese Heuchelei WM Fußball, dabei gab es in Katar schon mehrere WM z.B. Handball WM war ein großer Erfolg ohne Vorkommnisse. Diese Vollidioten sollen ihr Hirn einschalten .Doppelmoral.",
    "created_at": "2022-11-20T08:25:17.000Z",
    "public_metrics": {
      "retweet_count": 1,
      "reply_count": 0,
      "like_count": 1,
      "quote_count": 0
    }
  },
  "1594245469735198721": {
    "text": "Nur bei den England Fans kann ich glauben, dass die wirklich alle so aussehen. Die Arbekter kommen eh alle aus Indien. #FIFAWorldCup https://t.co/P5Es8FQdVD",
    "created_at": "2022-11-20T08:25:14.000Z",
    "public_metrics": {
      "retweet_count": 0,
      "reply_count": 0,
      "like_count": 0,
      "quote_count": 0
    }
  },
  "1594245337551900674": {
    "text": "für mich kommt da nur boykott in frage.\n#MagentaWM #WMBoykott #WM2022 #Katar2022",
    "created_at": "2022-11-20T08:24:42.000Z",
    "public_metrics": {
      "retweet_count": 0,
      "reply_count": 1,
      "like_count": 5,
      "quote_count": 0
    }
  },
  "1594245033565511684": {
    "text": "Irgendwie werd ich das Gefühl nicht los, dass das Problem mit der WM in Qatar sich nicht auf Menschenrechte bezieht sondern sich eher auf den Islam und Muslime richtet 👀",
    "created_at": "2022-11-20T08:23:30.000Z",
    "public_metrics": {
      "retweet_count": 0,
      "reply_count": 5,
      "like_count": 16,
      "quote_count": 1
    }
  },
  "1594244946634194945": {
    "text": "Wer schaut heute die Eröffnung?\n#WM2022 #WMBoykott",
    "created_at": "2022-11-20T08:23:09.000Z",
    "public_metrics": {
      "retweet_count": 0,
      "reply_count": 0,
      "like_count": 0,
      "quote_count": 0
    }
  },
  "1594244875628814336": {
    "text": "WM in Russland = 👍\nOlympiade in China = 👍 \nWM in Qatar = 🙅🏼‍♂️🛑🤮 *mEnScHenRecHtsvErleTzung* \n\nWer findet das wirkliche Problem?",
    "created_at": "2022-11-20T08:22:52.000Z",
    "public_metrics": {
      "retweet_count": 5,
      "reply_count": 2,
      "like_count": 12,
      "quote_count": 2
    }
  },
  "1594244863221850112": {
    "text": "Heute geht es endlich los, mit der #WM2022 die #WM2022 unterm Weihnachtsbaum 😂😂😂😂 hat auch Mal was.",
    "created_at": "2022-11-20T08:22:49.000Z",
    "public_metrics": {
      "retweet_count": 0,
      "reply_count": 0,
      "like_count": 1,
      "quote_count": 0
    }
  },
  "1594244693222883329": {
    "text": "Viele haben die Meinung ein Boykott der WM bringe nichts und sei scheinheilig. Klar hätte man bereits bei der Vergabe aufpassen müssen und die WM nicht nach Katar vergeben dürfen. Aber die Fifa Pressekonferenz war gelinde gesagt skurril. Der Boykott ist nicht nur \n\n #MagentaWM",
    "created_at": "2022-11-20T08:22:09.000Z",
    "public_metrics": {
      "retweet_count": 4,
      "reply_count": 4,
      "like_count": 23,
      "quote_count": 0
    }
  },
  "1594244321028481024": {
    "text": "Ist es Zufall, dass #Totensonntag und der Beginn des #FIFAWorldCup heute beide auf denselben Tag fallen? https://t.co/05uRvJoG24",
    "created_at": "2022-11-20T08:20:40.000Z",
    "public_metrics": {
      "retweet_count": 0,
      "reply_count": 0,
      "like_count": 3,
      "quote_count": 0
    }
  },
  "1594244309779451905": {
    "text": "Totensonntag.\n\nEin wunderbarer Tag, um eine WM in Katar zu beginnen\n\n#WM2022 #Qatar2022 #QatarWorldCup2022",
    "created_at": "2022-11-20T08:20:37.000Z",
    "public_metrics": {
      "retweet_count": 0,
      "reply_count": 0,
      "like_count": 1,
      "quote_count": 0
    }
  },
  "1594244275503783936": {
    "text": "Die Macher schwärmen schon jetzt von der Eröffnungsfeier für #Qatar2022. #WM2022 \n\nhttps://t.co/pRtsPt7lZx",
    "created_at": "2022-11-20T08:20:29.000Z",
    "public_metrics": {
      "retweet_count": 0,
      "reply_count": 0,
      "like_count": 0,
      "quote_count": 0
    }
  },
  "1594244269413650432": {
    "text": "In Zukunft wird Qatar Deutschland jährlich 25.000 bezahlte Fans liefern. Diese Rent-a-Fans sollen dann in Deutschland unbeliebten Politikern wie Olaf Scholz, Robert Habeck und Annalena Baerbock bei öffentlichen Reden frenetisch zujubeln.\nhttps://t.co/1pSeEt7IhO\n#WM2022 https://t.co/IqQvynt6Nq",
    "created_at": "2022-11-20T08:20:28.000Z",
    "public_metrics": {
      "retweet_count": 0,
      "reply_count": 0,
      "like_count": 1,
      "quote_count": 0
    }
  },
  "1594244216674304000": {
    "text": "Wer ab heute keine #WM2022 sehen will, ist bei #ARD und #ZDF echt in den Bobbes gekniffen. Kein attraktives Alternativ Programm. Die Streamingdienste wirds freuen.",
    "created_at": "2022-11-20T08:20:15.000Z",
    "public_metrics": {
      "retweet_count": 0,
      "reply_count": 0,
      "like_count": 0,
      "quote_count": 0
    }
  },
  "1594244164597727233": {
    "text": "Zum Start der #WM2022 hat die @fdp eine besondere Überraschung für den @DFB vorbereitet ⚽️ Die FDP will  künftig einen strengen Vergabekodex - u.a. ein „Demokratiesiegel“👏👏 @DjirSarai https://t.co/93mwNJ7eCK",
    "created_at": "2022-11-20T08:20:03.000Z",
    "public_metrics": {
      "retweet_count": 0,
      "reply_count": 1,
      "like_count": 0,
      "quote_count": 0
    }
  },
  "1594244071891296256": {
    "text": "Heute bin ich beim Sonntagsstammtsich im #BR zu Gast. Ab 11 Uhr diskutiere ich u.a. über die Lage in der #Ukraine und die #WM in #Katar. Einschalten lohnt sich bestimmt! 😎 #Sonntag #stammtisch #bayern #weltmeisterschaft @bayerischer_rundfunk https://t.co/YOmrQj5Glw",
    "created_at": "2022-11-20T08:19:41.000Z",
    "public_metrics": {
      "retweet_count": 5,
      "reply_count": 6,
      "like_count": 29,
      "quote_count": 0
    }
  },
  "1594243999577305093": {
    "text": "Die Emirate wollen während der WM für die Unterhaltung der Fans sorgen. Zwischen Katar und Dubai wurde eine Luftbrücke errichtet. ⬇️ https://t.co/KYekeLrydw",
    "created_at": "2022-11-20T08:19:23.000Z",
    "public_metrics": {
      "retweet_count": 0,
      "reply_count": 0,
      "like_count": 1,
      "quote_count": 0
    }
  },
  "1594243926331899904": {
    "text": "WM 2022: Kontroverses Turnier in Katar beginnt | #PCLMedia https://t.co/VyLg4IGpGF\n\n#sport #FussballWM #Gesellschaft #Fussball #Katar #Infantino #Menschenrechte https://t.co/4cu4JyJKVC",
    "created_at": "2022-11-20T08:19:06.000Z",
    "public_metrics": {
      "retweet_count": 0,
      "reply_count": 0,
      "like_count": 0,
      "quote_count": 0
    }
  },
  "1594243713974534144": {
    "text": "Nach der Beinahe-Blamage gegen Oman lautet unsere Frage der Woche im #DOPA:\nWie weit kommt die deutsche Nationalmannschaft bei der WM? #DFBTeam #WM2022",
    "created_at": "2022-11-20T08:18:15.000Z",
    "public_metrics": {
      "retweet_count": 3,
      "reply_count": 129,
      "like_count": 59,
      "quote_count": 1
    }
  },
  "1594243488425590786": {
    "text": "Heute beginnt die WM im Katar. Australien  Japan, Südkorea und die USA müssen sich verarscht vorkommen.",
    "created_at": "2022-11-20T08:17:21.000Z",
    "public_metrics": {
      "retweet_count": 0,
      "reply_count": 2,
      "like_count": 3,
      "quote_count": 0
    }
  },
  "1594243388823535616": {
    "text": "Das Tagebuch zur WM in Katar: Metallgitter brechen den Willen der WM-Besucher\n#123INFO\nhttps://t.co/7V8hHgXWX8",
    "created_at": "2022-11-20T08:16:58.000Z",
    "public_metrics": {
      "retweet_count": 0,
      "reply_count": 0,
      "like_count": 0,
      "quote_count": 0
    }
  },
  "1594243294468640768": {
    "text": "WM 2022 in Katar - Favoriten, Außenseiter, Geheimtipps: Hier sind alle 32 Teams im Check https://t.co/rcPwMP99jF https://t.co/4vKE2oGktz",
    "created_at": "2022-11-20T08:16:35.000Z",
    "public_metrics": {
      "retweet_count": 0,
      "reply_count": 0,
      "like_count": 0,
      "quote_count": 0
    }
  },
  "1594243241196818432": {
    "text": "Mein einziger Post zur #WM2022\nGuckt Euch diese Seite an:\n\nhttps://t.co/EXe0NM6yU0\n\n#BoycottQatar2022",
    "created_at": "2022-11-20T08:16:22.000Z",
    "public_metrics": {
      "retweet_count": 1,
      "reply_count": 0,
      "like_count": 6,
      "quote_count": 0
    }
  },
  "1594243097537515521": {
    "text": "Ich find Fußball scheisse. Find es auch scheisse wie die Menschen in Katar behandelt werden. Hab aber in meiner Therapie gelernt, steigere dich nicht in Sachen rein die du nicht ändern kannst #QatarWorldCup2022",
    "created_at": "2022-11-20T08:15:48.000Z",
    "public_metrics": {
      "retweet_count": 0,
      "reply_count": 0,
      "like_count": 0,
      "quote_count": 0
    }
  },
  "1594243052788482049": {
    "text": "Fußball-WM in Katar: Kontroverse Fußball-WM begleitet von politischen Debatten\nhttps://t.co/MPar1rbiqA\n🇩🇪 Aktuelle Nachrichten\n#aktuellenachrichten #nachrichten #Deutschlands #Europa #aktuelle",
    "created_at": "2022-11-20T08:15:38.000Z",
    "public_metrics": {
      "retweet_count": 0,
      "reply_count": 0,
      "like_count": 0,
      "quote_count": 0
    }
  },
  "1594243049655341057": {
    "text": "WM-Prognose: Qatar gewinnt das Eröffnungsspiel nicht\nhttps://t.co/J70ZeWZcQ0\n🇩🇪 Aktuelle Nachrichten\n#aktuellenachrichten #nachrichten #Deutschlands #Europa #aktuelle",
    "created_at": "2022-11-20T08:15:37.000Z",
    "public_metrics": {
      "retweet_count": 0,
      "reply_count": 0,
      "like_count": 0,
      "quote_count": 0
    }
  },
  "1594243019791749120": {
    "text": "WM 2022 in Katar: Telegramm aus Doha – Jetzt gibt es kein Zurück mehr\nhttps://t.co/FkyEISJEHD\n🇩🇪 Aktuelle Nachrichten\n#aktuellenachrichten #nachrichten #Deutschlands #Europa #aktuelle",
    "created_at": "2022-11-20T08:15:30.000Z",
    "public_metrics": {
      "retweet_count": 0,
      "reply_count": 0,
      "like_count": 0,
      "quote_count": 0
    }
  },
  "1594243017715879937": {
    "text": "Fußball-WM 2022 in Katar: Bundestrainer Hansi Flick lehnt Angebot von Jogi Löw ab\nhttps://t.co/ulntQ538Ki\n🇩🇪 Aktuelle Nachrichten\n#aktuellenachrichten #nachrichten #Deutschlands #Europa #aktuelle",
    "created_at": "2022-11-20T08:15:29.000Z",
    "public_metrics": {
      "retweet_count": 0,
      "reply_count": 0,
      "like_count": 0,
      "quote_count": 0
    }
  },
  "1594242964368543744": {
    "text": "Heute geht die #WM2022 los - lol.\n\n#TwitchDE\n#SupportSmallStreamers #smallstreamers #wm #sport #FussballWM #goodmorning #SundayFunday #SmallStreamersConnect #SmallStreamerCommunity",
    "created_at": "2022-11-20T08:15:16.000Z",
    "public_metrics": {
      "retweet_count": 3,
      "reply_count": 0,
      "like_count": 4,
      "quote_count": 0
    }
  },
  "1594242857484910592": {
    "text": "Die repressiven Kräfte der Islamischen Republik haben Mahabad mit Panzern, Mannschaftstransportern und Waffen angegriffen, lasst uns die Stimme von #Mahabad sein. @UN\n#مهسا_امینی\n#FIFAWorldCup",
    "created_at": "2022-11-20T08:14:51.000Z",
    "public_metrics": {
      "retweet_count": 4,
      "reply_count": 0,
      "like_count": 2,
      "quote_count": 0
    }
  },
  "1594242842314133505": {
    "text": "Wir werden ganz sicher alle vor der Glotze sitzen und heulen.\n*\nBeginn der WM in #Qatar: \"Das traurigste Turnier aller Zeiten\" - https://t.co/ZlarUfoNZ6.",
    "created_at": "2022-11-20T08:14:47.000Z",
    "public_metrics": {
      "retweet_count": 0,
      "reply_count": 0,
      "like_count": 0,
      "quote_count": 0
    }
  },
  "1594242535555465217": {
    "text": "Das Tagebuch zur WM in Katar: Metallgitter brechen den Willen der WM-Besucher https://t.co/rwtyosmc1H",
    "created_at": "2022-11-20T08:13:34.000Z",
    "public_metrics": {
      "retweet_count": 1,
      "reply_count": 0,
      "like_count": 0,
      "quote_count": 0
    }
  },
  "1594242393909272576": {
    "text": "DAS WEISS NATÜRLICH AUCH DER GROSSE UÖI HOENESS, EINER GROSSEN FÖRDERER KATARS WIE FRANZ BECKENBAUER!: Justizminister Buschmann zu Eklat um WM-Botschafter: »Homosexualität ist keine Krankheit« https://t.co/VgGZqJYxBK via @derspiegel https://t.co/Uu2x7mzvlL",
    "created_at": "2022-11-20T08:13:00.000Z",
    "public_metrics": {
      "retweet_count": 0,
      "reply_count": 0,
      "like_count": 0,
      "quote_count": 0
    }
  },
  "1594242270970400768": {
    "text": "Auf gehts Deutschland 🇩🇪\n @DFB_Team #FIFAWorldCup https://t.co/EkQzxwYjUl",
    "created_at": "2022-11-20T08:12:31.000Z",
    "public_metrics": {
      "retweet_count": 1,
      "reply_count": 0,
      "like_count": 5,
      "quote_count": 0
    }
  },
  "1594242177906999296": {
    "text": "Nach dem Katzbuckel des grünen Parteifreundes Habeck...\nhttps://t.co/oa9SSrDTDq",
    "created_at": "2022-11-20T08:12:09.000Z",
    "public_metrics": {
      "retweet_count": 0,
      "reply_count": 0,
      "like_count": 1,
      "quote_count": 0
    }
  },
  "1594242102631616512": {
    "text": "Die Islamische Republik hat in #Mahabad den Strom abgestellt und begeht im Blackout der Stadt Verbrechen und massakriert protestierende Menschen.\n#FIFAWorldCup              \n#MahsaAmini",
    "created_at": "2022-11-20T08:11:51.000Z",
    "public_metrics": {
      "retweet_count": 5,
      "reply_count": 0,
      "like_count": 1,
      "quote_count": 0
    }
  },
  "1594241997778616323": {
    "text": "WM in Katar: Kaum Public Viewing in Segeberg https://t.co/o9hR66UbJt",
    "created_at": "2022-11-20T08:11:26.000Z",
    "public_metrics": {
      "retweet_count": 0,
      "reply_count": 0,
      "like_count": 0,
      "quote_count": 0
    }
  },
  "1594241893071732736": {
    "text": "Pedro Lenz: Warum ich trotz allem Fussball-WM schaue https://t.co/VHIeXyJBV7",
    "created_at": "2022-11-20T08:11:01.000Z",
    "public_metrics": {
      "retweet_count": 0,
      "reply_count": 3,
      "like_count": 1,
      "quote_count": 0
    }
  },
  "1594241802877358080": {
    "text": "Null! Sie interessiert mich Null, diese Kasperveranstaltung…und das ist so, obwohl ich die heutige politische Empörung für bigott und vor allem verspätet halte. Der ausgeuferte Spitzenfußball in seiner Parallelwelt ist der Grund für mein totales Desinteresse #WM2022",
    "created_at": "2022-11-20T08:10:40.000Z",
    "public_metrics": {
      "retweet_count": 0,
      "reply_count": 1,
      "like_count": 4,
      "quote_count": 0
    }
  },
  "1594241750604075008": {
    "text": "#FIFAWorldCup Es ist frustrierend, wie sich #Infantino und #FIFA mit fragwürdigen Ausreden um die eigene Verantwortung drücken. Wir fordern weiter Entschädigungen für Arbeitsmigrant*innen in #Katar! https://t.co/3PwwepjuEY #FußballJaAusbeutungNein #Menschenrechte",
    "created_at": "2022-11-20T08:10:27.000Z",
    "public_metrics": {
      "retweet_count": 3,
      "reply_count": 0,
      "like_count": 7,
      "quote_count": 0
    }
  },
  "1594241719771750401": {
    "text": "Am widerlichsten und zugleich auch am traurigsten sind doch Regime wie das der FIFA oder Regime wie das von Katar und auch die vielen anderen Regime, in denen die Mächtigen nur einem Grundsatz kennen: Dass man sich mit Geld alles kaufen kann. #FIFAWorldCup",
    "created_at": "2022-11-20T08:10:20.000Z",
    "public_metrics": {
      "retweet_count": 26,
      "reply_count": 58,
      "like_count": 347,
      "quote_count": 2
    }
  },
  "1594241384126349313": {
    "text": "Heute beginnt die #WM2022, die niemals nach Katar hätte vergeben werden dürfen. Zur \"Einstimmung\" empfehlen wir heute das erschütternde Interview mit Kennedy, der von seiner Zeit als Arbeitssklave in Katar berichtet. \n\n#BoykottQatar2022 \n#NichtunsereWM\nhttps://t.co/YYHqIgNSYa",
    "created_at": "2022-11-20T08:09:00.000Z",
    "public_metrics": {
      "retweet_count": 28,
      "reply_count": 2,
      "like_count": 76,
      "quote_count": 0
    }
  },
  "1594241350991577088": {
    "text": "Nun geht also das Schauspiel Fußball-Weltmeisterschaft in Katar los… gespielt wird in Stadien, die extra gekühlt werden müssen um überhaupt spielen zu können und deren Errichtung über 15.000 Tote forderte.. die Welt ist krank.. die Krankheit heißt Mensch #BoycottQatar2022 https://t.co/PJlwr9i3r6",
    "created_at": "2022-11-20T08:08:52.000Z",
    "public_metrics": {
      "retweet_count": 0,
      "reply_count": 0,
      "like_count": 5,
      "quote_count": 0
    }
  },
  "1594241174415761409": {
    "text": "#Infantino könnte leider sagen was er will. Einfach alles. Die WM würde man trotzdem anpfeifen, die Sendeanstalten würde trotzdem übertragen, Werbepartner würden nicht abspringen und Millionen Fans würden weiterhin zuschauen bzw. würden nach Katar fliegen.",
    "created_at": "2022-11-20T08:08:10.000Z",
    "public_metrics": {
      "retweet_count": 0,
      "reply_count": 0,
      "like_count": 0,
      "quote_count": 0
    }
  },
  "1594241011219402752": {
    "text": "Fußball-WM: Al-Bayt-Stadion - Ort der Eröffnung, Ort der Ausbeutung https://t.co/MkVR8WkwfC #FußballWM #Katar #FIFA",
    "created_at": "2022-11-20T08:07:31.000Z",
    "public_metrics": {
      "retweet_count": 21,
      "reply_count": 141,
      "like_count": 122,
      "quote_count": 5
    }
  },
  "1594240960220864513": {
    "text": "11 Dinge, die du tun kannst, wenn andere Fußball schauen #Stuttgart #WM https://t.co/KGKUHr83Ku https://t.co/iXLZDR0OZT",
    "created_at": "2022-11-20T08:07:19.000Z",
    "public_metrics": {
      "retweet_count": 0,
      "reply_count": 1,
      "like_count": 0,
      "quote_count": 0
    }
  },
  "1594240909457371137": {
    "text": "Habe die nächsten 4 Wochen wohl einen leichten \"Katar\" und werde leider die WM nicht sehen können. Wirklich schade.",
    "created_at": "2022-11-20T08:07:07.000Z",
    "public_metrics": {
      "retweet_count": 2,
      "reply_count": 4,
      "like_count": 17,
      "quote_count": 0
    }
  },
  "1594240521572356096": {
    "text": "WM-Ticketpreisanalyse: ​So teuer waren WM-Tickets noch nie  #2022 #Fußball #FußballWeltmeisterschaft #FußballWM #Katar #Weltmeisterschaft #WMTickets\n\nhttps://t.co/yjzFphC147",
    "created_at": "2022-11-20T08:05:34.000Z",
    "public_metrics": {
      "retweet_count": 1,
      "reply_count": 0,
      "like_count": 0,
      "quote_count": 0
    }
  },
  "1594240504186691586": {
    "text": "Ein toller morgen, um eine Weltmeisterschaft zu boykottieren.\n#FIFAWorldCup #BoykottQatar2022 https://t.co/W28WE30KwL",
    "created_at": "2022-11-20T08:05:30.000Z",
    "public_metrics": {
      "retweet_count": 0,
      "reply_count": 1,
      "like_count": 7,
      "quote_count": 1
    }
  },
  "1594240423585013762": {
    "text": "Ich boykottiere diese WM da in #Katar wirklich! \n\nAber nicht wegen Katar, sondern weil ich Eishockey nicht mag!",
    "created_at": "2022-11-20T08:05:11.000Z",
    "public_metrics": {
      "retweet_count": 4,
      "reply_count": 23,
      "like_count": 101,
      "quote_count": 0
    }
  },
  "1594240237177393154": {
    "text": "Thema Fußball: \n1. wir hatten eine Wm in Russland (niemanden juckt es)\n2. wir hatten olympia in China (niemanden juckt es)\n3. unsere vereine lassen sich von den emiraten sponsorn (bayern mit qatar airways\n4. simpler Kulturimperialismus",
    "created_at": "2022-11-20T08:04:26.000Z",
    "public_metrics": {
      "retweet_count": 0,
      "reply_count": 0,
      "like_count": 3,
      "quote_count": 0
    }
  },
  "1594240121079037955": {
    "text": "Am Sonntag beginnt die WM. Viele Fans winken ab, die Gastgeber hatten sich die Sache auch anders vorgestellt. Doch nur mit Pauschalkritik wird sich in Qatar und im internationalen Fußball nichts bewegen. Was folgt aus dem umstrittenen Turnier? https://t.co/GxnvhCiwDH",
    "created_at": "2022-11-20T08:03:59.000Z",
    "public_metrics": {
      "retweet_count": 3,
      "reply_count": 2,
      "like_count": 2,
      "quote_count": 0
    }
  },
  "1594240120219176960": {
    "text": "Am Sonntag beginnt die WM. Viele Fans winken ab, die Gastgeber hatten sich die Sache auch anders vorgestellt. Doch nur mit Pauschalkritik wird sich in Qatar und im internationalen Fußball nichts bewegen. Was folgt aus dem umstrittenen Turnier? https://t.co/68A9YP7aGg",
    "created_at": "2022-11-20T08:03:58.000Z",
    "public_metrics": {
      "retweet_count": 0,
      "reply_count": 1,
      "like_count": 1,
      "quote_count": 1
    }
  },
  "1594240119304757248": {
    "text": "Am Sonntag beginnt die WM. Viele Fans winken ab, die Gastgeber hatten sich die Sache auch anders vorgestellt. Doch nur mit Pauschalkritik wird sich in Qatar und im internationalen Fußball nichts bewegen. Was folgt aus dem umstrittenen Turnier? https://t.co/smeN8Ery4K",
    "created_at": "2022-11-20T08:03:58.000Z",
    "public_metrics": {
      "retweet_count": 1,
      "reply_count": 2,
      "like_count": 1,
      "quote_count": 0
    }
  },
  "1594240072941027328": {
    "text": "Was haben die Fußball WM in Katar und Wetten, dass ... gemeinsam? Richtig.",
    "created_at": "2022-11-20T08:03:47.000Z",
    "public_metrics": {
      "retweet_count": 0,
      "reply_count": 0,
      "like_count": 0,
      "quote_count": 0
    }
  },
  "1594240064338419713": {
    "text": "#220Millionen haben @ARD_Presse und @ZDF (also wir alle) für die Übertragung des #FIFAWorldCup    aus #Katar gezahlt. \n\nÜber #20Millionen im Jahr verdienen die bestbezahlten Spieler des @DFB_Team\n\n#1Million spendet das @DFB_Team pressewirksam an ein Kinderdorf in Nepal.",
    "created_at": "2022-11-20T08:03:45.000Z",
    "public_metrics": {
      "retweet_count": 3,
      "reply_count": 2,
      "like_count": 17,
      "quote_count": 0
    }
  },
  "1594239920696360961": {
    "text": "Eröffnungsspiel - WM 2022: Katar gegen Ecuador live im Internet schauen https://t.co/N17mObjWlK https://t.co/YFAua8oR3Q",
    "created_at": "2022-11-20T08:03:11.000Z",
    "public_metrics": {
      "retweet_count": 0,
      "reply_count": 0,
      "like_count": 0,
      "quote_count": 0
    }
  },
  "1594239911494025216": {
    "text": "Helmut Markworts Tagebuch - Warum ich mir trotz aller Boykottaufrufe die WM in Katar ansehe https://t.co/MVsGtTp8P2 https://t.co/mqKIoRAfHg",
    "created_at": "2022-11-20T08:03:09.000Z",
    "public_metrics": {
      "retweet_count": 0,
      "reply_count": 0,
      "like_count": 0,
      "quote_count": 0
    }
  },
  "1594239890262310913": {
    "text": "#Infantino ist der erste der sich homosexuell fühlt bei dem ich wirklich einen „damage in the mind“ befürchte. #QatarWorldCup2022 #WM2022",
    "created_at": "2022-11-20T08:03:04.000Z",
    "public_metrics": {
      "retweet_count": 0,
      "reply_count": 1,
      "like_count": 5,
      "quote_count": 0
    }
  },
  "1594239889528061952": {
    "text": "Heute beginnt in #Katar die umstrittenste Fußball-WM aller Zeiten. Grünen-Vorsitzende @Ricarda_Lang fordert: Wer vor Ort ist, sollte den „Finger in die Wunde legen“. #WM2022 https://t.co/41BFLImprc",
    "created_at": "2022-11-20T08:03:03.000Z",
    "public_metrics": {
      "retweet_count": 9,
      "reply_count": 136,
      "like_count": 17,
      "quote_count": 9
    }
  },
  "1594239882079051776": {
    "text": "Amnesty: \"Es braucht Druck auf die FIFA\" https://t.co/jBEwYLeEdd",
    "created_at": "2022-11-20T08:03:02.000Z",
    "public_metrics": {
      "retweet_count": 18,
      "reply_count": 32,
      "like_count": 86,
      "quote_count": 1
    }
  },
  "1594239632849469440": {
    "text": "Christina Graf kommentiert als erste Frau Spiele bei einer Männer-Fußball-WM live im @daserste. Ihr Blick auf die deutsche Mannschaft ist sehr optimistisch - und was sie sonst vom #FIFAWorldCup hält, erzählt sie in #SWR1 Leute, heute  10 Uhr. @ard_presse https://t.co/4fGtVelx5D",
    "created_at": "2022-11-20T08:02:02.000Z",
    "public_metrics": {
      "retweet_count": 0,
      "reply_count": 3,
      "like_count": 2,
      "quote_count": 0
    }
  },
  "1594239589115625472": {
    "text": "Eröffnung und Schlüsselspiel für Katar und Ecuador https://t.co/iq0iaakOjL #sportnews #bluesport",
    "created_at": "2022-11-20T08:01:52.000Z",
    "public_metrics": {
      "retweet_count": 0,
      "reply_count": 0,
      "like_count": 0,
      "quote_count": 0
    }
  },
  "1594239562393726976": {
    "text": "Alternativen zur WM in Katar: 11 Dinge, die du tun kannst, wenn andere Fußball schauen https://t.co/f35gPb9gKR https://t.co/vq3XtHt0Yk",
    "created_at": "2022-11-20T08:01:45.000Z",
    "public_metrics": {
      "retweet_count": 0,
      "reply_count": 0,
      "like_count": 0,
      "quote_count": 0
    }
  },
  "1594239548397334528": {
    "text": "#BoycottQatar2022 #QatarWorldCup2022\n#FIFAWorldCup\n#MAFIFA\n#FIFAWorldCupOpening\nDER WESTEN: WM 2022: Ungeheure Enthüllung zu Eröffnungsspiel – Insider erheben heftige Vorwürfe.\nhttps://t.co/Wgv3eCfP2I\n\nüber @GoogleNews",
    "created_at": "2022-11-20T08:01:42.000Z",
    "public_metrics": {
      "retweet_count": 0,
      "reply_count": 0,
      "like_count": 0,
      "quote_count": 0
    }
  },
  "1594239520479870977": {
    "text": "Von „Monstern“, Schicksalsschlägen und ­Tänzern: Sie sind nicht die Besten, aber die Besonderen. F.A.Z.-Autoren stellen sieben Fußballprofis vor, die bei der WM ins Scheinwerferlicht drängen. #Qatar2022 https://t.co/BgaxoCinwV",
    "created_at": "2022-11-20T08:01:35.000Z",
    "public_metrics": {
      "retweet_count": 0,
      "reply_count": 0,
      "like_count": 0,
      "quote_count": 0
    }
  },
  "1594239519611559936": {
    "text": "Von „Monstern“, Schicksalsschlägen und ­Tänzern: Sie sind nicht die Besten, aber die Besonderen. F.A.Z.-Autoren stellen sieben Fußballprofis vor, die bei der WM ins Scheinwerferlicht drängen. #Qatar2022 https://t.co/l5vkQgHCFF",
    "created_at": "2022-11-20T08:01:35.000Z",
    "public_metrics": {
      "retweet_count": 0,
      "reply_count": 1,
      "like_count": 0,
      "quote_count": 0
    }
  },
  "1594239440981053441": {
    "text": "Die Fußball-WM in Katar ist eine großartige Werbung für den Sport. Also für Handball, Eishockey, Basketball etc.\n#WM2022",
    "created_at": "2022-11-20T08:01:16.000Z",
    "public_metrics": {
      "retweet_count": 29,
      "reply_count": 10,
      "like_count": 275,
      "quote_count": 0
    }
  },
  "1594239397767303168": {
    "text": "WM 2022: Katar zwingt Stadionbesucher umstrittene Apps zu installieren https://t.co/JENOr6VA7O via @basicthinking #mtp #cybersecurity",
    "created_at": "2022-11-20T08:01:06.000Z",
    "public_metrics": {
      "retweet_count": 3,
      "reply_count": 0,
      "like_count": 2,
      "quote_count": 0
    }
  },
  "1594239342930972672": {
    "text": "wer sich den Kracher Katar-Ecuador nicht anguckt, hat den Fussball nie geliebt. \n\n#Qatar #QatarWorldCup2022 #WM2022 #WMderSchande #FIFAWorldCup #wm #Katar #Katar2022",
    "created_at": "2022-11-20T08:00:53.000Z",
    "public_metrics": {
      "retweet_count": 0,
      "reply_count": 0,
      "like_count": 3,
      "quote_count": 0
    }
  },
  "1594239342519762944": {
    "text": "Fifa-Präsident Gianni Infantino meint, die Kritik an der Herrenfußball-WM sollte sich nicht gegen Katar richten, sondern wenn überhaupt gegen ihn.\n\nFairer Punkt. Ich boykottiere nicht mehr die WM in Katar, sondern nur noch die WM, die Gianni Infantino ausrichtet.",
    "created_at": "2022-11-20T08:00:53.000Z",
    "public_metrics": {
      "retweet_count": 36,
      "reply_count": 14,
      "like_count": 1122,
      "quote_count": 0
    }
  },
  "1594239291521380358": {
    "text": "Ab heute rollt der Ball wieder...⚽️ Wir drücken unserer #Nationalmannschaft die Daumen für die #Fußballweltmeisterschaft in #Qatar2022!🏆 Am Mittwoch um 14 Uhr tritt Deutschland im 1. Spiel gegen Japan an. Wer gewinnt? Mit welchem Ergebnis rechnet ihr? #Fussball #wm2022 https://t.co/QaMS6chmVX",
    "created_at": "2022-11-20T08:00:41.000Z",
    "public_metrics": {
      "retweet_count": 0,
      "reply_count": 0,
      "like_count": 0,
      "quote_count": 0
    }
  },
  "1594239259413725184": {
    "text": "The ** Daily wurde soeben publiziert! https://t.co/4cKyCm0HhJ Vielen Dank an @SkySportDE #wm2022",
    "created_at": "2022-11-20T08:00:33.000Z",
    "public_metrics": {
      "retweet_count": 0,
      "reply_count": 0,
      "like_count": 0,
      "quote_count": 0
    }
  },
  "1594239258411270145": {
    "text": "WM 2022: Benzema verpasst WM in Katar https://t.co/k8RhBLZvIA von @SkySportNewsHD #wm2022",
    "created_at": "2022-11-20T08:00:33.000Z",
    "public_metrics": {
      "retweet_count": 0,
      "reply_count": 0,
      "like_count": 0,
      "quote_count": 0
    }
  },
  "1594239250735992832": {
    "text": "Stell dir vor es ist Fussball WM und keiner schaut hin. #WM2022 \n\n(Leider wieder nur ein Spruch)",
    "created_at": "2022-11-20T08:00:31.000Z",
    "public_metrics": {
      "retweet_count": 0,
      "reply_count": 0,
      "like_count": 0,
      "quote_count": 0
    }
  },
  "1594239216002764801": {
    "text": "Sicherheit bei der WM: 15 deutsche Panzer, die sich die Ukraine jetzt wünscht, verkaufte Merkel nach Katar https://t.co/TpoG0yAeh7 via @welt     Die Ukraine wünscht, dass wäre mal ganz was Neues. Die fordern doch immer nur.",
    "created_at": "2022-11-20T08:00:23.000Z",
    "public_metrics": {
      "retweet_count": 0,
      "reply_count": 0,
      "like_count": 0,
      "quote_count": 0
    }
  },
  "1594239196948054016": {
    "text": "Tausende Arbeitsmigranten sind beim Bau der WM-Stadien in Katar gestorben. Trotz drakonischen Regeln und dem Verbot von Gewerkschaften, schaffen sie es, sich zu organisieren und für ihre Rechte zu kämpfen\n\nVon Jörn Boewe\n\nhttps://t.co/WtyYUSDIJr",
    "created_at": "2022-11-20T08:00:18.000Z",
    "public_metrics": {
      "retweet_count": 0,
      "reply_count": 1,
      "like_count": 6,
      "quote_count": 0
    }
  }
}
