{
  "1603620441297502208": {
    "text": "#MoroccoVsFrance \nKein Wort dazu bei Konserven und Liberallalas. Kein Wort bei Speichelt und #HaltDieFresseSpringerPresse \n\nEmpfehlenswerter Beitrag aus FAZnet: \n https://t.co/2xjdJJZXCN",
    "created_at": "2022-12-16T05:18:01.000Z",
    "public_metrics": {
      "retweet_count": 5,
      "reply_count": 0,
      "like_count": 11,
      "quote_count": 0
    }
  },
  "1603620327958929408": {
    "text": "Nächste Jugend-WM-Medaille für Mia Griesel aus Tostedt https://t.co/2PFBsQI6Sj https://t.co/jXm5kBxfz1",
    "created_at": "2022-12-16T05:17:34.000Z",
    "public_metrics": {
      "retweet_count": 0,
      "reply_count": 0,
      "like_count": 0,
      "quote_count": 0
    }
  },
  "1603619971401240577": {
    "text": "Traumstart in #Grinch-Outfit: Titelverteidiger Peter #Wright glänzt zum Auftakt der #DartsWM\n\n➡️https://t.co/ECYjzHyD18 https://t.co/FtTUaDyIQJ",
    "created_at": "2022-12-16T05:16:09.000Z",
    "public_metrics": {
      "retweet_count": 0,
      "reply_count": 0,
      "like_count": 1,
      "quote_count": 0
    }
  },
  "1603619921598025729": {
    "text": "Wer die Bundesliga im WM-Finale vertritt https://t.co/mOcDDFGeJM https://t.co/08I0aaiLsk",
    "created_at": "2022-12-16T05:15:57.000Z",
    "public_metrics": {
      "retweet_count": 0,
      "reply_count": 0,
      "like_count": 0,
      "quote_count": 0
    }
  },
  "1603618006172856320": {
    "text": "Die denkwürdigsten WM-Momente: Messi pöbelt, Boufal tanzt, Ronaldo verschwindet: Was für eine WM! https://t.co/q1rN4Xvsei https://t.co/hnZyfw0vp7",
    "created_at": "2022-12-16T05:08:21.000Z",
    "public_metrics": {
      "retweet_count": 0,
      "reply_count": 0,
      "like_count": 0,
      "quote_count": 0
    }
  },
  "1603617918595391488": {
    "text": "Nur als nette Geste? #Frankreichs Final-Plan mit Karim #Benzema. ⚽️\n#WM2022 #ranfussball \nhttps://t.co/OlKSEMgnmF",
    "created_at": "2022-12-16T05:08:00.000Z",
    "public_metrics": {
      "retweet_count": 0,
      "reply_count": 1,
      "like_count": 11,
      "quote_count": 0
    }
  },
  "1603617602806456327": {
    "text": "Wer die Bundesliga im WM-Finale vertritt https://t.co/WdxnqmSjbe",
    "created_at": "2022-12-16T05:06:44.000Z",
    "public_metrics": {
      "retweet_count": 0,
      "reply_count": 0,
      "like_count": 0,
      "quote_count": 0
    }
  },
  "1603617449911500803": {
    "text": "Fazit zur WM in Katar: Schrecklich und schön zugleich\nhttps://t.co/MoUkQtqHxg",
    "created_at": "2022-12-16T05:06:08.000Z",
    "public_metrics": {
      "retweet_count": 0,
      "reply_count": 0,
      "like_count": 0,
      "quote_count": 0
    }
  },
  "1603617032217534464": {
    "text": "WM | Das Finale im Hörfunk &amp; TV: Drei Reportagen, zwei Premieren - https://t.co/VB04o3qxCr | Das Finale im Hörfunk &amp; TV: Drei Reportagen, zwei Premieren https://t.co/uT09tYiXuE",
    "created_at": "2022-12-16T05:04:28.000Z",
    "public_metrics": {
      "retweet_count": 0,
      "reply_count": 0,
      "like_count": 0,
      "quote_count": 0
    }
  },
  "1603616552716312577": {
    "text": "Philipp #Lahm kritisiert #FIFA-Präsident Gianni #Infantino scharf: \"Er macht sich das Spiel zunutze\" #Qatar2022\n\n➡️https://t.co/GvJCMZ9Hba https://t.co/d7majljHy3",
    "created_at": "2022-12-16T05:02:34.000Z",
    "public_metrics": {
      "retweet_count": 0,
      "reply_count": 0,
      "like_count": 0,
      "quote_count": 0
    }
  },
  "1603616162205548544": {
    "text": "Vergleich zwischen ARD-WM-Moderatorin und Pitbull sorgt für Diskussionen\nhttps://t.co/j5oM5pvgTF https://t.co/Bn3FhClgOd",
    "created_at": "2022-12-16T05:01:01.000Z",
    "public_metrics": {
      "retweet_count": 0,
      "reply_count": 0,
      "like_count": 0,
      "quote_count": 0
    }
  },
  "1603616090034262018": {
    "text": "FC Bayern hinter Atlético: Vereine mit meisten Spielern im WM-Finale #FCBayern https://t.co/8GPgaKiNGV",
    "created_at": "2022-12-16T05:00:44.000Z",
    "public_metrics": {
      "retweet_count": 0,
      "reply_count": 0,
      "like_count": 1,
      "quote_count": 0
    }
  },
  "1603614194774966272": {
    "text": "EU-Vizeparlamentspräsidentin Kaili verliert alle Befugnisse https://t.co/n8A9Eh24Yk",
    "created_at": "2022-12-16T04:53:12.000Z",
    "public_metrics": {
      "retweet_count": 0,
      "reply_count": 0,
      "like_count": 0,
      "quote_count": 0
    }
  },
  "1603612667318607877": {
    "text": "Upamecano, Palacios und Co. | Wer die Bundesliga im WM-Finale vertritt - https://t.co/4OHg1n2T9G, Palacios und Co. | Wer die Bundesliga im WM-Finale vertritt https://t.co/dUl1hCSgqh",
    "created_at": "2022-12-16T04:47:08.000Z",
    "public_metrics": {
      "retweet_count": 0,
      "reply_count": 0,
      "like_count": 0,
      "quote_count": 0
    }
  },
  "1603612391396319232": {
    "text": "Philipp Lahm kritisiert Fifa-Boss Gianni Infantino scharf: Verband hat „an Glaubwürdigkeit verloren“\nhttps://t.co/7ycuRelmEJ",
    "created_at": "2022-12-16T04:46:02.000Z",
    "public_metrics": {
      "retweet_count": 0,
      "reply_count": 0,
      "like_count": 0,
      "quote_count": 0
    }
  },
  "1603609621440221186": {
    "text": "➠ Halbfinale bei der Fußball-WM: Marokko weiß jetzt, woran es noch fehlt\n\n» Auf zu neuen Grenzen: Marokko scheitert zwar im Halbfinale an Frankreich, der Erfolg bei dieser WM dürfte trotzdem nachwirken - auch in der Karriereplanung einzelner Spieler.\n \n  https://t.co/LeRU7UVMMA",
    "created_at": "2022-12-16T04:35:02.000Z",
    "public_metrics": {
      "retweet_count": 0,
      "reply_count": 0,
      "like_count": 0,
      "quote_count": 0
    }
  },
  "1603607299888918528": {
    "text": "Das Einzige, was ich aus der Zeit der WM mitgenommen habe, ist ein Katarrh.",
    "created_at": "2022-12-16T04:25:48.000Z",
    "public_metrics": {
      "retweet_count": 1,
      "reply_count": 0,
      "like_count": 1,
      "quote_count": 0
    }
  }
}
